tarshim/__init__.py
tarshim/demo_utils.py
tarshim/notebook_image_handling.py
tarshim/tarshim.py
tarshim/tmp.py
tarshim-1.0.0.dist-info/LICENSE
tarshim-1.0.0.dist-info/METADATA
tarshim-1.0.0.dist-info/WHEEL
tarshim-1.0.0.dist-info/top_level.txt
tarshim-1.0.0.dist-info/RECORD
