Metadata-Version: 2.1
Name: tarshim
Version: 1.0.0
Summary: Neat plot handling in python
Home-page: https://github.com/bgbg/tarshim
Author: Boris Gorelik
Author-email: boris@gorelik.net
Classifier: Programming Language :: Python :: 3
Classifier: License :: OSI Approved :: MIT License
Classifier: Operating System :: OS Independent
Requires-Python: >=3.6
License-File: LICENSE
Requires-Dist: jupyter
Requires-Dist: matplotlib
Requires-Dist: seaborn
